setup.py
WebDepCompress.egg-info/PKG-INFO
WebDepCompress.egg-info/SOURCES.txt
WebDepCompress.egg-info/dependency_links.txt
WebDepCompress.egg-info/namespace_packages.txt
WebDepCompress.egg-info/top_level.txt
webdepcompress/__init__.py
webdepcompress/manager.py
webdepcompress/support.py
webdepcompress/compressors/__init__.py
webdepcompress/compressors/base.py
webdepcompress/compressors/naive.py