Metadata-Version: 1.0
Name: WebDepCompress
Version: 0.2
Summary: JavaScript and CSS Compression Package
Home-page: http://dev.pocoo.org/hg/webdepcompress/
Author: Armin Ronacher
Author-email: armin.ronacher@active-4.com
License: BSD
Platform: any
